LICENSE
MANIFEST.in
README.rst
setup.cfg
setup.py
bin/greco
greco/__init__.py
greco/dotty-tea-pot.png
greco/eztext.py
greco/levels1.json
greco/levels2.json
greco.egg-info/PKG-INFO
greco.egg-info/SOURCES.txt
greco.egg-info/dependency_links.txt
greco.egg-info/entry_points.txt
greco.egg-info/requires.txt
greco.egg-info/top_level.txt
greco/sounds/00.ogg
greco/sounds/01.ogg
greco/sounds/02.ogg
greco/sounds/03.ogg
greco/sounds/04.ogg
greco/sounds/05.ogg
greco/sounds/06.ogg
greco/sounds/07.ogg
greco/sounds/08.ogg
greco/sounds/09.ogg
greco/sounds/10.ogg
greco/sounds/11.ogg
greco/sounds/12.ogg
greco/sounds/13.ogg
greco/sounds/14.ogg
greco/sounds/15.ogg
greco/sounds/16.ogg
greco/sounds/17.ogg
greco/sounds/18.ogg
greco/sounds/19.ogg
greco/sounds/20.ogg
greco/sounds/21.ogg
greco/sounds/22.ogg
greco/sounds/23.ogg
greco/sounds/24.ogg
greco/sounds/25.ogg
greco/sounds/26.ogg
greco/sounds/27.ogg
greco/sounds/28.ogg
greco/sounds/29.ogg
greco/sounds/30.ogg
greco/sounds/31.ogg
greco/sounds/32.ogg
greco/sounds/33.ogg
greco/sounds/34.ogg
greco/sounds/35.ogg
greco/sounds/36.ogg
greco/sounds/37.ogg
greco/sounds/38.ogg
greco/sounds/39.ogg
greco/sounds/40.ogg
greco/sounds/41.ogg
greco/sounds/42.ogg
greco/sounds/43.ogg
greco/sounds/44.ogg
greco/sounds/45.ogg
greco/sounds/46.ogg
greco/sounds/47.ogg
greco/sounds/48.ogg
greco/sounds/49.ogg
greco/sounds/50.ogg
greco/sounds/51.ogg
greco/sounds/52.ogg
greco/sounds/53.ogg
greco/sounds/54.ogg
greco/sounds/55.ogg
greco/sounds/56.ogg
greco/sounds/57.ogg
greco/sounds/58.ogg
greco/sounds/59.ogg
greco/sounds/60.ogg
greco/sounds/61.ogg
greco/sounds/62.ogg
greco/sounds/63.ogg