Metadata-Version: 1.1
Name: greco
Version: 0.1.4.1
Summary: a fun typing game for learning the Green Code visual language.
Home-page: http://ledui.github.io/
Author: Zeth
Author-email: theology@gmail.com
License: GPL
Platform: UNKNOWN
Classifier: Programming Language :: Python :: 2.7
Classifier: Programming Language :: Python :: 3
Classifier: Intended Audience :: Developers
Classifier: License :: OSI Approved :: BSD License
Classifier: Topic :: Software Development :: Libraries
Classifier: Topic :: Utilities
